README.md
setup.py
mosaiq_field_export/__init__.py
mosaiq_field_export/mosaiq_field_export.py
mosaiq_field_export.egg-info/PKG-INFO
mosaiq_field_export.egg-info/SOURCES.txt
mosaiq_field_export.egg-info/dependency_links.txt
mosaiq_field_export.egg-info/requires.txt
mosaiq_field_export.egg-info/top_level.txt