Metadata-Version: 1.0
Name: mosaiq-field-export
Version: 0.3.2
Summary: A toolbox for extracting field data from Mosaiq SQL.
Home-page: UNKNOWN
Author: Simon Biggs
Author-email: mail@simonbiggs.net
License: AGPL3+
Platform: UNKNOWN
